chatwidget/__init__.py
chatwidget/apps.py
chatwidget/openai_utils.py
chatwidget/urls.py
chatwidget/views.py
django_chatwidget-0.1.1.dist-info/licenses/LICENSE
django_chatwidget-0.1.1.dist-info/METADATA
django_chatwidget-0.1.1.dist-info/WHEEL
django_chatwidget-0.1.1.dist-info/top_level.txt
django_chatwidget-0.1.1.dist-info/RECORD
