Metadata-Version: 2.4
Name: django-chatwidget
Version: 0.1.1
Summary: A customizable, OpenAI-powered chat widget for Django projects
Home-page: https://github.com/mattyray/django-chatwidget
Author: Matthew Raynor
Author-email: Matthew Raynor <mnraynor90@gmail.com>
License: MIT
Project-URL: Homepage, https://github.com/mattyray/django-chatwidget
Project-URL: Repository, https://github.com/mattyray/django-chatwidget
Requires-Python: >=3.8
License-File: LICENSE
Requires-Dist: django>=3.2
Requires-Dist: openai>=1.0.0
Dynamic: license-file
